<?xml version="1.0" encoding="utf-8"?>
<RVPresentationDocument height="1080" width="1920" docType="0" versionNumber="600" usedCount="0" backgroundColor="0 0 0 1" drawingBackgroundColor="false" CCLIDisplay="false" lastDateUsed="" selectedArrangementID="" category="Presentation" resourcesDirectory="" notes="" CCLIAuthor="" CCLIArtistCredits="" CCLISongTitle="[[+title]]" CCLIPublisher="" CCLICopyrightYear="" CCLISongNumber="" chordChartPath="" os="1" buildNumber="6016">
    <RVTimeline timeOffset="0" duration="0" selectedMediaTrackIndex="-1" loop="false" rvXMLIvarName="timeline">
        <array rvXMLIvarName="timeCues" />
        <array rvXMLIvarName="mediaTracks" />
    </RVTimeline>
    <array rvXMLIvarName="groups">
        <RVSlideGrouping name="" color="1 1 1 0" uuid="27D6831C-8E77-4D0A-8FEA-F08140180B7A">
            <array rvXMLIvarName="slides">
                [[+slides]]
            </array>
        </RVSlideGrouping>
    </array>
    <array rvXMLIvarName="arrangements" />
</RVPresentationDocument>